trackpy/__init__.py
trackpy/_version.py
trackpy/api.py
trackpy/artificial.py
trackpy/diag.py
trackpy/feature.py
trackpy/feature_numba.py
trackpy/filtering.py
trackpy/framewise_data.py
trackpy/linking.py
trackpy/masks.py
trackpy/motion.py
trackpy/plots.py
trackpy/predict.py
trackpy/preprocessing.py
trackpy/static.py
trackpy/tracking.py
trackpy/try_numba.py
trackpy/uncertainty.py
trackpy/utils.py
trackpy-0.3.3.dist-info/DESCRIPTION.rst
trackpy-0.3.3.dist-info/METADATA
trackpy-0.3.3.dist-info/RECORD
trackpy-0.3.3.dist-info/WHEEL
trackpy-0.3.3.dist-info/metadata.json
trackpy-0.3.3.dist-info/top_level.txt
