Metadata-Version: 2.0
Name: trackpy
Version: 0.3.3
Summary: particle-tracking toolkit
Home-page: https://github.com/soft-matter/trackpy
Author: Trackpy Contributors
Author-email: daniel.b.allan@gmail.com
License: UNKNOWN
Platform: UNKNOWN
Requires-Dist: matplotlib
Requires-Dist: numpy (>=1.7)
Requires-Dist: pandas (>=0.13)
Requires-Dist: pims (>=0.3.3)
Requires-Dist: pyyaml
Requires-Dist: scipy (>=0.12)
Requires-Dist: six (>=1.8)
